hera_pspec/__init__.py
hera_pspec/_version.py
hera_pspec/container.py
hera_pspec/conversions.py
hera_pspec/grouping.py
hera_pspec/noise.py
hera_pspec/parameter.py
hera_pspec/plot.py
hera_pspec/pspecbeam.py
hera_pspec/pspecdata.py
hera_pspec/pstokes.py
hera_pspec/testing.py
hera_pspec/utils.py
hera_pspec/uvpspec.py
hera_pspec/uvpspec_utils.py
hera_pspec/uvwindow.py
hera_pspec/version.py
hera_pspec/data/__init__.py
hera_pspec/tests/__init__.py
hera_pspec/tests/compare_legacy_oqe.py
hera_pspec/tests/test_container.py
hera_pspec/tests/test_conversions.py
hera_pspec/tests/test_grouping.py
hera_pspec/tests/test_noise.py
hera_pspec/tests/test_plot.py
hera_pspec/tests/test_pspecbeam.py
hera_pspec/tests/test_pspecdata.py
hera_pspec/tests/test_pstokes.py
hera_pspec/tests/test_testing.py
hera_pspec/tests/test_utils.py
hera_pspec/tests/test_uvpspec.py
hera_pspec/tests/test_uvpspec_utils.py
hera_pspec/tests/test_uvwindow.py
hera_pspec-0.4.1.data/scripts/auto_noise_run.py
hera_pspec-0.4.1.data/scripts/bootstrap_run.py
hera_pspec-0.4.1.data/scripts/generate_pstokes_run.py
hera_pspec-0.4.1.data/scripts/pspec_red.py
hera_pspec-0.4.1.data/scripts/pspec_run.py
hera_pspec-0.4.1.dist-info/LICENSE
hera_pspec-0.4.1.dist-info/METADATA
hera_pspec-0.4.1.dist-info/WHEEL
hera_pspec-0.4.1.dist-info/top_level.txt
hera_pspec-0.4.1.dist-info/RECORD
